{
   "abstract" : "MIME::BaseX - Encoding and decoding of base16, base32, base64 and base64url",
   "author" : [
      "Lucas Tiago de Moraes"
   ],
   "dynamic_config" : 0,
   "generated_by" : "ExtUtils::MakeMaker version 7.36, CPAN::Meta::Converter version 2.150010",
   "license" : [
      "perl_5"
   ],
   "meta-spec" : {
      "url" : "http://search.cpan.org/perldoc?CPAN::Meta::Spec",
      "version" : 2
   },
   "name" : "MIME-BaseX",
   "no_index" : {
      "directory" : [
         "t",
         "inc"
      ]
   },
   "prereqs" : {
      "build" : {
         "requires" : {
            "ExtUtils::MakeMaker" : "0"
         }
      },
      "configure" : {
         "requires" : {
            "ExtUtils::MakeMaker" : "0"
         }
      },
      "runtime" : {
         "requires" : {
            "Exporter" : "5.57",
            "MIME::Base64" : "3.11",
            "XSLoader" : "0",
            "perl" : "5.008005"
         }
      }
   },
   "release_status" : "stable",
   "resources" : {
      "bugtracker" : {
         "web" : "https://github.com/lucas1/MIME-BaseX/issues"
      },
      "homepage" : "https://github.com/lucas1/MIME-BaseX",
      "repository" : {
         "type" : "git",
         "web" : "https://github.com/lucas1/MIME-BaseX"
      }
   },
   "version" : "0.01",
   "x_serialization_backend" : "JSON::PP version 4.02"
}
